simple_channel_log/__init__.py
simple_channel_log/i fastapi_journallog.py
simple_channel_log/i simple_channel_log.py
simple_channel_log-1.8.2.dist-info/licenses/LICENSE
simple_channel_log-1.8.2.dist-info/METADATA
simple_channel_log-1.8.2.dist-info/WHEEL
simple_channel_log-1.8.2.dist-info/top_level.txt
simple_channel_log-1.8.2.dist-info/RECORD
