Metadata-Version: 2.4
Name: simple-channel-log
Version: 1.8.2
Summary: 轻量高效的日志库，支持多级别日志记录、日志轮转、流水日志追踪及埋点日志功能，深度集成 Flask，FastAPI，Requests，Unirest 以及 CTEC-Consumer 框架。
Author: Unnamed great master
Author-email: <gqylpy@outlook.com>
License: MIT
Project-URL: Source, https://github.com/2018-11-27/simple-channel-log
Classifier: Development Status :: 3 - Alpha
Classifier: Intended Audience :: Developers
Classifier: License :: OSI Approved :: MIT License
Classifier: Natural Language :: Chinese (Simplified)
Classifier: Natural Language :: English
Classifier: Operating System :: OS Independent
Classifier: Topic :: Software Development :: Libraries :: Python Modules
Classifier: Topic :: Artistic Software
Classifier: Topic :: Internet :: Log Analysis
Classifier: Topic :: Text Processing
Classifier: Programming Language :: Python :: 2.7
Classifier: Programming Language :: Python :: 3.0
Classifier: Programming Language :: Python :: 3.1
Classifier: Programming Language :: Python :: 3.2
Classifier: Programming Language :: Python :: 3.3
Classifier: Programming Language :: Python :: 3.4
Classifier: Programming Language :: Python :: 3.5
Classifier: Programming Language :: Python :: 3.6
Classifier: Programming Language :: Python :: 3.7
Classifier: Programming Language :: Python :: 3.8
Classifier: Programming Language :: Python :: 3.9
Classifier: Programming Language :: Python :: 3.10
Classifier: Programming Language :: Python :: 3.11
Classifier: Programming Language :: Python :: 3.12
Classifier: Programming Language :: Python :: 3.13
Requires-Python: >=2.7
License-File: LICENSE
Requires-Dist: gqylpy_log==0.0a1
Requires-Dist: ipaddress<2.0,>=1.0.23
Provides-Extra: flask
Requires-Dist: Flask>=0.10; extra == "flask"
Provides-Extra: requests
Requires-Dist: requests>=2.19; extra == "requests"
Provides-Extra: fastapi
Requires-Dist: fastapi>=0.83.0; extra == "fastapi"
Provides-Extra: unirest
Requires-Dist: unirest>=1.0.5; extra == "unirest"
Provides-Extra: ctec-consumer
Requires-Dist: ctec-consumer>=0.1; extra == "ctec-consumer"
Dynamic: author
Dynamic: author-email
Dynamic: classifier
Dynamic: description
Dynamic: description-content-type
Dynamic: license
Dynamic: license-file
Dynamic: project-url
Dynamic: provides-extra
Dynamic: requires-dist
Dynamic: requires-python
Dynamic: summary
